bidsphysio/__init__.py
bidsphysio/info.py
bidsphysio-21.6.24.dist-info/LICENSE
bidsphysio-21.6.24.dist-info/METADATA
bidsphysio-21.6.24.dist-info/WHEEL
bidsphysio-21.6.24.dist-info/top_level.txt
bidsphysio-21.6.24.dist-info/RECORD
