Metadata-Version: 2.1
Name: bidsphysio
Version: 21.6.24
Summary: Physio-to-BIDS Converter
Home-page: UNKNOWN
Author: Pablo Velasco
Author-email: pablo.velasco@nyu.edu
License: MIT
Platform: UNKNOWN
Classifier: Environment :: Console
Classifier: Intended Audience :: Science/Research
Classifier: License :: OSI Approved :: MIT License
Classifier: Programming Language :: Python :: 3.6
Classifier: Programming Language :: Python :: 3.7
Classifier: Programming Language :: Python :: 3.8
Classifier: Topic :: Scientific/Engineering
Requires-Python: >=3.6
Requires-Dist: bidsphysio.dcm2bids
Requires-Dist: bidsphysio.pmu2bids
Requires-Dist: bidsphysio.events
Requires-Dist: bidsphysio.session
Requires-Dist: bidsphysio.acq2bids
Requires-Dist: bidsphysio.edf2bids
Requires-Dist: bidsphysio.base
Requires-Dist: bidsphysio.physio2bids
Provides-Extra: all
Requires-Dist: pytest ; extra == 'all'
Provides-Extra: tests
Requires-Dist: pytest ; extra == 'tests'
